test_add_python.cpython-38-x86_64-linux-gnu.so
test_add_python-1.3.dist-info/METADATA
test_add_python-1.3.dist-info/WHEEL
test_add_python-1.3.dist-info/top_level.txt
test_add_python-1.3.dist-info/RECORD
.libstest_add_python/libcudart-4554289f.so.11.5.117
.libstest_add_python/libgomp-38ea1071.so.1.0.0
