Metadata-Version: 2.1
Name: test_add_python
Version: 1.3
Author: Dmitry Michaylin
